DataOCREnhance/DataOCREnhance.py
DataOCREnhance/__init__.py
DataOCREnhance-0.0.1.dist-info/LICENSE
DataOCREnhance-0.0.1.dist-info/METADATA
DataOCREnhance-0.0.1.dist-info/WHEEL
DataOCREnhance-0.0.1.dist-info/top_level.txt
DataOCREnhance-0.0.1.dist-info/RECORD
