Metadata-Version: 2.1
Name: DataOCREnhance
Version: 0.0.1
Summary: A toolkit for performing OCR (Optical Character Recognition) tasks
Home-page: https://github.com/your_username/ocr_toolkit
Author: IoT Noob Talha Khalid
Author-email: zjohndavid88@gmail.com
Classifier: Programming Language :: Python :: 3
Classifier: License :: OSI Approved :: MIT License
Classifier: Operating System :: OS Independent
License-File: LICENSE
Requires-Dist: Pillow
Requires-Dist: pytesseract
Requires-Dist: opencv-python
Requires-Dist: numpy
Requires-Dist: nltk
